{"nodes": [{"id": "surrogate_pool_py", "label": "pool.py", "file_type": "code", "source_file": "surrogate/pool.py", "source_location": "L1"}, {"id": "pool_solutionpool", "label": "SolutionPool", "file_type": "code", "source_file": "surrogate/pool.py", "source_location": "L16"}, {"id": "pool_solutionpool_init", "label": ".__init__()", "file_type": "code", "source_file": "surrogate/pool.py", "source_location": "L22"}, {"id": "pool_solutionpool_initialize", "label": ".initialize()", "file_type": "code", "source_file": "surrogate/pool.py", "source_location": "L30"}, {"id": "pool_solutionpool_update", "label": ".update()", "file_type": "code", "source_file": "surrogate/pool.py", "source_location": "L41"}, {"id": "pool_solutionpool_best", "label": ".best()", "file_type": "code", "source_file": "surrogate/pool.py", "source_location": "L53"}, {"id": "pool_solutionpool_all", "label": ".all()", "file_type": "code", "source_file": "surrogate/pool.py", "source_location": "L57"}, {"id": "pool_solutionpool_len", "label": ".__len__()", "file_type": "code", "source_file": "surrogate/pool.py", "source_location": "L61"}, {"id": "pool_solutionpool_trim", "label": "._trim()", "file_type": "code", "source_file": "surrogate/pool.py", "source_location": "L68"}, {"id": "pool_rationale_1", "label": "Solution Pool  \u7ba1\u7406\u4e00\u7ec4\u5019\u9009\u89e3\uff08pool_size=40\uff09\uff0c\u652f\u6301\uff1a - \u521d\u59cb\u5316\uff08\u4ece\u5355\u4e2a\u6216\u591a\u4e2a\u89e3\u586b\u5145\uff09 - \u66f4\u65b0\uff08\u65b0\u65e7\u5408\u5e76\u53d6 top-K\uff09 - \u6392\u5e8f", "file_type": "rationale", "source_file": "surrogate/pool.py", "source_location": "L1"}, {"id": "pool_rationale_17", "label": "\u7ef4\u62a4 top-K \u6700\u4f18\u89e3\u7684\u89e3\u6c60\u3002      \u6392\u5e8f\u4f9d\u636e\uff1aObjectiveValue \u5b57\u5178\u5e8f\uff08splits \u2192 cost \u2192 time\uff09\u3002", "file_type": "rationale", "source_file": "surrogate/pool.py", "source_location": "L17"}, {"id": "pool_rationale_31", "label": "\u7528\u7ed9\u5b9a\u89e3\u5217\u8868\u521d\u59cb\u5316 pool\u3002          \u6bcf\u4e2a\u89e3\u4f1a\u8ba1\u7b97\u76ee\u6807\u51fd\u6570\u503c\uff08\u82e5\u5c1a\u672a\u8ba1\u7b97\uff09\u3002", "file_type": "rationale", "source_file": "surrogate/pool.py", "source_location": "L31"}, {"id": "pool_rationale_42", "label": "\u5c06\u65b0\u89e3\u4e0e\u5f53\u524d pool \u5408\u5e76\uff0c\u53d6 top-K\u3002          spec \u00a74.3\uff1a\u65b0 40 \u4e2a + \u65e7 40 \u4e2a\u5408\u5e76\uff0c\u5b57\u5178\u5e8f\u6392\u5e8f\u53d6 top-40\u3002", "file_type": "rationale", "source_file": "surrogate/pool.py", "source_location": "L42"}, {"id": "pool_rationale_58", "label": "\u8fd4\u56de pool \u5185\u6240\u6709\u89e3\u7684\u526f\u672c\u5217\u8868\uff08\u987a\u5e8f\uff1a\u6700\u4f18\u5728\u524d\uff09\u3002", "file_type": "rationale", "source_file": "surrogate/pool.py", "source_location": "L58"}], "edges": [{"source": "surrogate_pool_py", "target": "models", "relation": "imports_from", "confidence": "EXTRACTED", "source_file": "surrogate/pool.py", "source_location": "L12", "weight": 1.0}, {"source": "surrogate_pool_py", "target": "oracle", "relation": "imports_from", "confidence": "EXTRACTED", "source_file": "surrogate/pool.py", "source_location": "L13", "weight": 1.0}, {"source": "surrogate_pool_py", "target": "pool_solutionpool", "relation": "contains", "confidence": "EXTRACTED", "source_file": "surrogate/pool.py", "source_location": "L16", "weight": 1.0}, {"source": "pool_solutionpool", "target": "pool_solutionpool_init", "relation": "method", "confidence": "EXTRACTED", "source_file": "surrogate/pool.py", "source_location": "L22", "weight": 1.0}, {"source": "pool_solutionpool", "target": "pool_solutionpool_initialize", "relation": "method", "confidence": "EXTRACTED", "source_file": "surrogate/pool.py", "source_location": "L30", "weight": 1.0}, {"source": "pool_solutionpool", "target": "pool_solutionpool_update", "relation": "method", "confidence": "EXTRACTED", "source_file": "surrogate/pool.py", "source_location": "L41", "weight": 1.0}, {"source": "pool_solutionpool", "target": "pool_solutionpool_best", "relation": "method", "confidence": "EXTRACTED", "source_file": "surrogate/pool.py", "source_location": "L53", "weight": 1.0}, {"source": "pool_solutionpool", "target": "pool_solutionpool_all", "relation": "method", "confidence": "EXTRACTED", "source_file": "surrogate/pool.py", "source_location": "L57", "weight": 1.0}, {"source": "pool_solutionpool", "target": "pool_solutionpool_len", "relation": "method", "confidence": "EXTRACTED", "source_file": "surrogate/pool.py", "source_location": "L61", "weight": 1.0}, {"source": "pool_solutionpool", "target": "pool_solutionpool_trim", "relation": "method", "confidence": "EXTRACTED", "source_file": "surrogate/pool.py", "source_location": "L68", "weight": 1.0}, {"source": "pool_solutionpool_initialize", "target": "pool_solutionpool_trim", "relation": "calls", "confidence": "EXTRACTED", "source_file": "surrogate/pool.py", "source_location": "L39", "weight": 1.0}, {"source": "pool_rationale_1", "target": "surrogate_pool_py", "relation": "rationale_for", "confidence": "EXTRACTED", "source_file": "surrogate/pool.py", "source_location": "L1", "weight": 1.0}, {"source": "pool_rationale_17", "target": "pool_solutionpool", "relation": "rationale_for", "confidence": "EXTRACTED", "source_file": "surrogate/pool.py", "source_location": "L17", "weight": 1.0}, {"source": "pool_rationale_31", "target": "pool_solutionpool_initialize", "relation": "rationale_for", "confidence": "EXTRACTED", "source_file": "surrogate/pool.py", "source_location": "L31", "weight": 1.0}, {"source": "pool_rationale_42", "target": "pool_solutionpool_update", "relation": "rationale_for", "confidence": "EXTRACTED", "source_file": "surrogate/pool.py", "source_location": "L42", "weight": 1.0}, {"source": "pool_rationale_58", "target": "pool_solutionpool_all", "relation": "rationale_for", "confidence": "EXTRACTED", "source_file": "surrogate/pool.py", "source_location": "L58", "weight": 1.0}]}